main.py
mseep_simplelocalize_mcp-0.1.4.dist-info/licenses/LICENSE
mseep_simplelocalize_mcp-0.1.4.dist-info/METADATA
mseep_simplelocalize_mcp-0.1.4.dist-info/WHEEL
mseep_simplelocalize_mcp-0.1.4.dist-info/entry_points.txt
mseep_simplelocalize_mcp-0.1.4.dist-info/top_level.txt
mseep_simplelocalize_mcp-0.1.4.dist-info/RECORD
